{
  "warnings": [
    {
      "file": "/Users/sbooth/Development/SFBAudioEngine/SFBAudioEngine/SFBAttachedPicture.h",
      "line": 70,
      "symbol": "SFBAttachedPicture.+new",
      "symbol_kind": "sourcekitten.source.lang.objc.decl.method.class",
      "warning": "undocumented"
    },
    {
      "file": "/Users/sbooth/Development/SFBAudioEngine/SFBAudioEngine/SFBAttachedPicture.h",
      "line": 71,
      "symbol": "SFBAttachedPicture.-init",
      "symbol_kind": "sourcekitten.source.lang.objc.decl.method.instance",
      "warning": "undocumented"
    },
    {
      "file": "/Users/sbooth/Development/SFBAudioEngine/SFBAudioEngine/SFBAudioConverter.h",
      "line": 49,
      "symbol": "SFBAudioConverter.+new",
      "symbol_kind": "sourcekitten.source.lang.objc.decl.method.class",
      "warning": "undocumented"
    },
    {
      "file": "/Users/sbooth/Development/SFBAudioEngine/SFBAudioEngine/SFBAudioConverter.h",
      "line": 50,
      "symbol": "SFBAudioConverter.-init",
      "symbol_kind": "sourcekitten.source.lang.objc.decl.method.instance",
      "warning": "undocumented"
    },
    {
      "file": "/Users/sbooth/Development/SFBAudioEngine/SFBAudioEngine/SFBAudioDecoder.h",
      "line": 59,
      "symbol": "SFBAudioDecoder.+new",
      "symbol_kind": "sourcekitten.source.lang.objc.decl.method.class",
      "warning": "undocumented"
    },
    {
      "file": "/Users/sbooth/Development/SFBAudioEngine/SFBAudioEngine/SFBAudioDecoder.h",
      "line": 60,
      "symbol": "SFBAudioDecoder.-init",
      "symbol_kind": "sourcekitten.source.lang.objc.decl.method.instance",
      "warning": "undocumented"
    },
    {
      "file": "/Users/sbooth/Development/SFBAudioEngine/SFBAudioEngine/SFBAudioDecoding.h",
      "line": 14,
      "symbol": "SFBAudioDecoding",
      "symbol_kind": "sourcekitten.source.lang.objc.decl.protocol",
      "warning": "undocumented"
    },
    {
      "file": "/Users/sbooth/Development/SFBAudioEngine/SFBAudioEngine/SFBAudioDevice.h",
      "line": 31,
      "symbol": "SFBAudioDevice.+new",
      "symbol_kind": "sourcekitten.source.lang.objc.decl.method.class",
      "warning": "undocumented"
    },
    {
      "file": "/Users/sbooth/Development/SFBAudioEngine/SFBAudioEngine/SFBAudioDevice.h",
      "line": 32,
      "symbol": "SFBAudioDevice.-init",
      "symbol_kind": "sourcekitten.source.lang.objc.decl.method.instance",
      "warning": "undocumented"
    },
    {
      "file": "/Users/sbooth/Development/SFBAudioEngine/SFBAudioEngine/SFBAudioDeviceDataSource.h",
      "line": 16,
      "symbol": "SFBAudioDeviceDataSource.+new",
      "symbol_kind": "sourcekitten.source.lang.objc.decl.method.class",
      "warning": "undocumented"
    },
    {
      "file": "/Users/sbooth/Development/SFBAudioEngine/SFBAudioEngine/SFBAudioDeviceDataSource.h",
      "line": 17,
      "symbol": "SFBAudioDeviceDataSource.-init",
      "symbol_kind": "sourcekitten.source.lang.objc.decl.method.instance",
      "warning": "undocumented"
    },
    {
      "file": "/Users/sbooth/Development/SFBAudioEngine/SFBAudioEngine/SFBAudioEncoder.h",
      "line": 57,
      "symbol": "SFBAudioEncoder.+new",
      "symbol_kind": "sourcekitten.source.lang.objc.decl.method.class",
      "warning": "undocumented"
    },
    {
      "file": "/Users/sbooth/Development/SFBAudioEngine/SFBAudioEngine/SFBAudioEncoder.h",
      "line": 58,
      "symbol": "SFBAudioEncoder.-init",
      "symbol_kind": "sourcekitten.source.lang.objc.decl.method.instance",
      "warning": "undocumented"
    },
    {
      "file": "/Users/sbooth/Development/SFBAudioEngine/SFBAudioEngine/SFBAudioEncoder.h",
      "line": 104,
      "symbol": "SFBAudioEncoder.-initWithOutputSource:encoderName:",
      "symbol_kind": "sourcekitten.source.lang.objc.decl.method.instance",
      "warning": "undocumented"
    },
    {
      "file": "/Users/sbooth/Development/SFBAudioEngine/SFBAudioEngine/SFBAudioEncoding.h",
      "line": 14,
      "symbol": "SFBAudioEncodingSettingsKey",
      "symbol_kind": "sourcekitten.source.lang.objc.decl.typedef",
      "warning": "undocumented"
    },
    {
      "file": "/Users/sbooth/Development/SFBAudioEngine/SFBAudioEngine/SFBAudioEncoding.h",
      "line": 15,
      "symbol": "SFBAudioEncodingSettingsValue",
      "symbol_kind": "sourcekitten.source.lang.objc.decl.typedef",
      "warning": "undocumented"
    },
    {
      "file": "/Users/sbooth/Development/SFBAudioEngine/SFBAudioEngine/SFBAudioEncoding.h",
      "line": 17,
      "symbol": "SFBAudioEncoding",
      "symbol_kind": "sourcekitten.source.lang.objc.decl.protocol",
      "warning": "undocumented"
    },
    {
      "file": "/Users/sbooth/Development/SFBAudioEngine/SFBAudioEngine/SFBAudioFile.h",
      "line": 34,
      "symbol": "SFBAudioFile.+new",
      "symbol_kind": "sourcekitten.source.lang.objc.decl.method.class",
      "warning": "undocumented"
    },
    {
      "file": "/Users/sbooth/Development/SFBAudioEngine/SFBAudioEngine/SFBAudioFile.h",
      "line": 35,
      "symbol": "SFBAudioFile.-init",
      "symbol_kind": "sourcekitten.source.lang.objc.decl.method.instance",
      "warning": "undocumented"
    },
    {
      "file": "/Users/sbooth/Development/SFBAudioEngine/SFBAudioEngine/SFBAudioMetadata.h",
      "line": 26,
      "symbol": "SFBAudioMetadataKey",
      "symbol_kind": "sourcekitten.source.lang.objc.decl.typedef",
      "warning": "undocumented"
    },
    {
      "file": "/Users/sbooth/Development/SFBAudioEngine/SFBAudioEngine/SFBAudioOutputDevice.h",
      "line": 14,
      "symbol": "SFBAudioOutputDevice",
      "symbol_kind": "sourcekitten.source.lang.objc.decl.class",
      "warning": "undocumented"
    },
    {
      "file": "/Users/sbooth/Development/SFBAudioEngine/SFBAudioEngine/SFBAudioPlayer.h",
      "line": 274,
      "symbol": "SFBAudioPlayerDelegate",
      "symbol_kind": "sourcekitten.source.lang.objc.decl.protocol",
      "warning": "undocumented"
    },
    {
      "file": "/Users/sbooth/Development/SFBAudioEngine/SFBAudioEngine/SFBAudioPlayerNode.h",
      "line": 24,
      "symbol": "SFBAudioPlayerNodePlaybackPosition",
      "symbol_kind": "sourcekitten.source.lang.objc.decl.typedef",
      "warning": "undocumented"
    },
    {
      "file": "/Users/sbooth/Development/SFBAudioEngine/SFBAudioEngine/SFBAudioPlayerNode.h",
      "line": 37,
      "symbol": "SFBAudioPlayerNodePlaybackTime",
      "symbol_kind": "sourcekitten.source.lang.objc.decl.typedef",
      "warning": "undocumented"
    },
    {
      "file": "/Users/sbooth/Development/SFBAudioEngine/SFBAudioEngine/SFBAudioPlayerNode.h",
      "line": 87,
      "symbol": "SFBAudioPlayerNode.-initWithRenderBlock:",
      "symbol_kind": "sourcekitten.source.lang.objc.decl.method.instance",
      "warning": "undocumented"
    },
    {
      "file": "/Users/sbooth/Development/SFBAudioEngine/SFBAudioEngine/SFBAudioPlayerNode.h",
      "line": 88,
      "symbol": "SFBAudioPlayerNode.-initWithFormat:renderBlock:",
      "symbol_kind": "sourcekitten.source.lang.objc.decl.method.instance",
      "warning": "undocumented"
    },
    {
      "file": "/Users/sbooth/Development/SFBAudioEngine/SFBAudioEngine/SFBAudioProperties.h",
      "line": 10,
      "symbol": "SFBAudioPropertiesKey",
      "symbol_kind": "sourcekitten.source.lang.objc.decl.typedef",
      "warning": "undocumented"
    },
    {
      "file": "/Users/sbooth/Development/SFBAudioEngine/SFBAudioEngine/SFBDSDDecoder.h",
      "line": 37,
      "symbol": "SFBDSDDecoder.+new",
      "symbol_kind": "sourcekitten.source.lang.objc.decl.method.class",
      "warning": "undocumented"
    },
    {
      "file": "/Users/sbooth/Development/SFBAudioEngine/SFBAudioEngine/SFBDSDDecoder.h",
      "line": 38,
      "symbol": "SFBDSDDecoder.-init",
      "symbol_kind": "sourcekitten.source.lang.objc.decl.method.instance",
      "warning": "undocumented"
    },
    {
      "file": "/Users/sbooth/Development/SFBAudioEngine/SFBAudioEngine/SFBDSDDecoding.h",
      "line": 10,
      "symbol": "SFBDSDDecoding",
      "symbol_kind": "sourcekitten.source.lang.objc.decl.protocol",
      "warning": "undocumented"
    },
    {
      "file": "/Users/sbooth/Development/SFBAudioEngine/SFBAudioEngine/SFBDSDPCMDecoder.h",
      "line": 14,
      "symbol": "SFBDSDPCMDecoder.+new",
      "symbol_kind": "sourcekitten.source.lang.objc.decl.method.class",
      "warning": "undocumented"
    },
    {
      "file": "/Users/sbooth/Development/SFBAudioEngine/SFBAudioEngine/SFBDSDPCMDecoder.h",
      "line": 15,
      "symbol": "SFBDSDPCMDecoder.-init",
      "symbol_kind": "sourcekitten.source.lang.objc.decl.method.instance",
      "warning": "undocumented"
    },
    {
      "file": "/Users/sbooth/Development/SFBAudioEngine/SFBAudioEngine/SFBDoPDecoder.h",
      "line": 15,
      "symbol": "SFBDoPDecoder.+new",
      "symbol_kind": "sourcekitten.source.lang.objc.decl.method.class",
      "warning": "undocumented"
    },
    {
      "file": "/Users/sbooth/Development/SFBAudioEngine/SFBAudioEngine/SFBDoPDecoder.h",
      "line": 16,
      "symbol": "SFBDoPDecoder.-init",
      "symbol_kind": "sourcekitten.source.lang.objc.decl.method.instance",
      "warning": "undocumented"
    },
    {
      "file": "/Users/sbooth/Development/SFBAudioEngine/SFBAudioEngine/SFBInputSource.h",
      "line": 95,
      "symbol": "SFBInputSource(SFBSignedIntegerReading)",
      "symbol_kind": "sourcekitten.source.lang.objc.decl.category",
      "warning": "undocumented"
    },
    {
      "file": "/Users/sbooth/Development/SFBAudioEngine/SFBAudioEngine/SFBInputSource.h",
      "line": 118,
      "symbol": "SFBInputSource(SFBUnsignedIntegerReading)",
      "symbol_kind": "sourcekitten.source.lang.objc.decl.category",
      "warning": "undocumented"
    },
    {
      "file": "/Users/sbooth/Development/SFBAudioEngine/SFBAudioEngine/SFBInputSource.h",
      "line": 141,
      "symbol": "SFBInputSource(SFBBigEndianReading)",
      "symbol_kind": "sourcekitten.source.lang.objc.decl.category",
      "warning": "undocumented"
    },
    {
      "file": "/Users/sbooth/Development/SFBAudioEngine/SFBAudioEngine/SFBInputSource.h",
      "line": 159,
      "symbol": "SFBInputSource(SFBLittleEndianReading)",
      "symbol_kind": "sourcekitten.source.lang.objc.decl.category",
      "warning": "undocumented"
    },
    {
      "file": "/Users/sbooth/Development/SFBAudioEngine/SFBAudioEngine/SFBLoopableRegionDecoder.h",
      "line": 13,
      "symbol": "SFBLoopableRegionDecoder.+new",
      "symbol_kind": "sourcekitten.source.lang.objc.decl.method.class",
      "warning": "undocumented"
    },
    {
      "file": "/Users/sbooth/Development/SFBAudioEngine/SFBAudioEngine/SFBLoopableRegionDecoder.h",
      "line": 14,
      "symbol": "SFBLoopableRegionDecoder.-init",
      "symbol_kind": "sourcekitten.source.lang.objc.decl.method.instance",
      "warning": "undocumented"
    },
    {
      "file": "/Users/sbooth/Development/SFBAudioEngine/SFBAudioEngine/SFBOutputSource.h",
      "line": 85,
      "symbol": "SFBOutputSource(SFBDataWriting)",
      "symbol_kind": "sourcekitten.source.lang.objc.decl.category",
      "warning": "undocumented"
    },
    {
      "file": "/Users/sbooth/Development/SFBAudioEngine/SFBAudioEngine/SFBOutputSource.h",
      "line": 95,
      "symbol": "SFBOutputSource(SFBSignedIntegerWriting)",
      "symbol_kind": "sourcekitten.source.lang.objc.decl.category",
      "warning": "undocumented"
    },
    {
      "file": "/Users/sbooth/Development/SFBAudioEngine/SFBAudioEngine/SFBOutputSource.h",
      "line": 118,
      "symbol": "SFBOutputSource(SFBUnsignedIntegerWriting)",
      "symbol_kind": "sourcekitten.source.lang.objc.decl.category",
      "warning": "undocumented"
    },
    {
      "file": "/Users/sbooth/Development/SFBAudioEngine/SFBAudioEngine/SFBOutputSource.h",
      "line": 141,
      "symbol": "SFBOutputSource(SFBBigEndianWriting)",
      "symbol_kind": "sourcekitten.source.lang.objc.decl.category",
      "warning": "undocumented"
    },
    {
      "file": "/Users/sbooth/Development/SFBAudioEngine/SFBAudioEngine/SFBOutputSource.h",
      "line": 159,
      "symbol": "SFBOutputSource(SFBLittleEndianWriting)",
      "symbol_kind": "sourcekitten.source.lang.objc.decl.category",
      "warning": "undocumented"
    },
    {
      "file": "/Users/sbooth/Development/SFBAudioEngine/SFBAudioEngine/SFBPCMDecoding.h",
      "line": 10,
      "symbol": "SFBPCMDecoding",
      "symbol_kind": "sourcekitten.source.lang.objc.decl.protocol",
      "warning": "undocumented"
    },
    {
      "file": "/Users/sbooth/Development/SFBAudioEngine/SFBAudioEngine/SFBPCMEncoding.h",
      "line": 10,
      "symbol": "SFBPCMEncoding",
      "symbol_kind": "sourcekitten.source.lang.objc.decl.protocol",
      "warning": "undocumented"
    },
    {
      "file": "/Users/sbooth/Development/SFBAudioEngine/SFBAudioEngine/SFBReplayGainAnalyzer.h",
      "line": 10,
      "symbol": "SFBReplayGainAnalyzerKey",
      "symbol_kind": "sourcekitten.source.lang.objc.decl.typedef",
      "warning": "undocumented"
    }
  ],
  "source_directory": "/Users/sbooth/Development/SFBAudioEngine"
}